CHANGELOG.md
README.md
cached_property/__init__.py
com.wyattbaldwin.cached_property-1.0.post2.dist-info/WHEEL
com.wyattbaldwin.cached_property-1.0.post2.dist-info/METADATA
com.wyattbaldwin.cached_property-1.0.post2.dist-info/RECORD
